yinhepy/YinHe.dll
yinhepy/ayinhe.pyc
yinhepy/interface.dll
yinhepy/libcurl.py
yinhepy/librist.dll
yinhepy/syse.dll
yinhepy/w32-pthreads.dll
yinhepy/yinhe.pyc
yinhepy/yinhehq.pyc
yinhe-1.3.12.dist-info/METADATA
yinhe-1.3.12.dist-info/WHEEL
yinhe-1.3.12.dist-info/top_level.txt
yinhe-1.3.12.dist-info/RECORD
