Metadata-Version: 2.1
Name: yinhe
Version: 1.3.12
Summary: A brief description of the package
Home-page: UNKNOWN
Author: yinhedata.com
License: UNKNOWN
Platform: UNKNOWN
Requires-Python: ==3.9
Requires-Dist: click
Requires-Dist: pandas
Requires-Dist: six
Requires-Dist: cryptography
Requires-Dist: akshare
